contextuals/__init__.py
contextuals/benchmarks/__init__.py
contextuals/benchmarks/analyzer.py
contextuals/benchmarks/cli.py
contextuals/benchmarks/model_benchmark.py
contextuals/cli.py
contextuals/core/cache.py
contextuals/core/config.py
contextuals/core/context_manager.py
contextuals/core/contextual.py
contextuals/core/exceptions.py
contextuals/location/__init__.py
contextuals/location/location_provider.py
contextuals/location/utils.py
contextuals/news/__init__.py
contextuals/news/news_provider.py
contextuals/news/utils.py
contextuals/system/__init__.py
contextuals/system/system_provider.py
contextuals/time/__init__.py
contextuals/time/time_provider.py
contextuals/time/utils.py
contextuals/weather/__init__.py
contextuals/weather/utils.py
contextuals/weather/weather_provider.py
contextuals-0.2.2.dist-info/LICENSE
contextuals-0.2.2.dist-info/METADATA
contextuals-0.2.2.dist-info/WHEEL
contextuals-0.2.2.dist-info/entry_points.txt
contextuals-0.2.2.dist-info/RECORD
