Metadata-Version: 2.3
Name: contextuals
Version: 0.2.2
Summary: A library for contextual information support in AI applications
License: MIT
Author: Laurent-Philippe Albou
Author-email: lpalbou@gmail.com
Requires-Python: >=3.9,<4.0
Classifier: License :: OSI Approved :: MIT License
Classifier: Programming Language :: Python :: 3
Classifier: Programming Language :: Python :: 3.9
Classifier: Programming Language :: Python :: 3.10
Classifier: Programming Language :: Python :: 3.11
Classifier: Programming Language :: Python :: 3.12
Classifier: Programming Language :: Python :: 3.13
Provides-Extra: benchmarks
Provides-Extra: cli
Provides-Extra: full
Requires-Dist: argparse (>=1.4.0,<2.0.0) ; extra == "cli" or extra == "full"
Requires-Dist: feedparser (>=6.0.10,<7.0.0)
Requires-Dist: jsonschema (>=4.19.1,<5.0.0)
Requires-Dist: pydantic-ai (>=0.0.14,<0.0.15) ; extra == "benchmarks" or extra == "full"
Requires-Dist: python-dotenv (>=1.0.0,<2.0.0)
Requires-Dist: pytz (>=2023.3,<2024.0)
Requires-Dist: requests (>=2.31.0,<3.0.0)
Project-URL: Repository, https://github.com/lpalbou/contextuals
